networkx_graph/__init__.py
networkx_graph/__main__.py
networkx_graph/_core.cp312-win_amd64.pyd
networkx_graph/_core.pyi
networkx_graph/py.typed
networkx_graph-0.2.5.dist-info/METADATA
networkx_graph-0.2.5.dist-info/WHEEL
networkx_graph-0.2.5.dist-info/licenses/LICENSE
networkx_graph-0.2.5.dist-info/RECORD
